augen/__init__.py
augen/main.py
augen-0.0.2.dist-info/LICENSE
augen-0.0.2.dist-info/METADATA
augen-0.0.2.dist-info/WHEEL
augen-0.0.2.dist-info/RECORD
